footballmvp/__init__.py
footballmvp/mvp_run.py
footballmvp-0.4.2.dist-info/licenses/LICENSE
footballmvp-0.4.2.dist-info/METADATA
footballmvp-0.4.2.dist-info/WHEEL
footballmvp-0.4.2.dist-info/top_level.txt
footballmvp-0.4.2.dist-info/RECORD
