Metadata-Version: 2.4
Name: footballmvp
Version: 0.4.2
Summary: Analytical tool to determine top performing football players (MVP) across leagues and tournaments.
Author-email: Drue Staples <druestaples@gmail.com>
License-Expression: MIT
Project-URL: Homepage, https://github.com/DrueStaples08/FootballMVP
Project-URL: Tracker, https://github.com/DrueStaples08/FootballMVP/issues
Keywords: football,soccer,mvp,analytics,sports,player,ball,goat
Classifier: Programming Language :: Python :: 3.12
Classifier: Operating System :: OS Independent
Classifier: Development Status :: 3 - Alpha
Classifier: Intended Audience :: Developers
Classifier: Topic :: Software Development :: Libraries
Requires-Python: >=3.12
License-File: LICENSE
Requires-Dist: requests>=2.32
Requires-Dist: pandas>=2.2
Requires-Dist: numpy>=2.1
Requires-Dist: beautifulsoup4>=4.12
Requires-Dist: selenium>=4.32
Requires-Dist: pyspark>=3.5
Requires-Dist: matplotlib>=3.9
Dynamic: license-file
